Workbook

Sheet Fluxo Diário
A1: Data | B1: Categoria | C1: Subcategoria | D1: Descrição | E1: Entrada R$ | F1: Saída R$ | G1: Saldo Acumulado R$
A2: 46081 | B2: Fornecedor | C2: Bebidas | D2: Distribuidora Norte | F2: 4247.26 | G2: =IFERROR(E2,0)-IFERROR(F2,0)
A3: 46082 | B3: Despesa variável | C3: Comissão | D3: Comissão garçom (dom) | F3: 1114.42 | G3: =G2+IFERROR(E3,0)-IFERROR(F3,0)
A4: 46082 | B4: Receita | C4: Cartão crédito | D4: Vendas do dia (dom) | E4: 6838.71 | G4: =G3+IFERROR(E4,0)-IFERROR(F4,0)
A5: 46082 | B5: Receita | C5: Cartão débito | D5: Vendas do dia (dom) | E5: 3343.37 | G5: =G4+IFERROR(E5,0)-IFERROR(F5,0)
A6: 46082 | B6: Receita | C6: PIX | D6: Vendas do dia (dom) | E6: 2735.48 | G6: =G5+IFERROR(E6,0)-IFERROR(F6,0)
A7: 46082 | B7: Receita | C7: Dinheiro | D7: Vendas do dia (dom) | E7: 759.86 | G7: =G6+IFERROR(E7,0)-IFERROR(F7,0)
A8: 46083 | B8: Fornecedor | C8: Hortifruti | D8: Feira semanal — Ceasa | F8: 1343.59 | G8: =G7+IFERROR(E8,0)-IFERROR(F8,0)
A9: 46083 | B9: Fornecedor | C9: Bebidas | D9: Distribuidora Norte | F9: 4130.87 | G9: =G8+IFERROR(E9,0)-IFERROR(F9,0)
A10: 46083 | B10: Receita | C10: Cartão crédito | D10: Vendas do dia (seg) | E10: 1591.88 | G10: =G9+IFERROR(E10,0)-IFERROR(F10,0)
A11: 46083 | B11: Receita | C11: Cartão débito | D11: Vendas do dia (seg) | E11: 778.25 | G11: =G10+IFERROR(E11,0)-IFERROR(F11,0)
A12: 46083 | B12: Receita | C12: PIX | D12: Vendas do dia (seg) | E12: 636.75 | G12: =G11+IFERROR(E12,0)-IFERROR(F12,0)
A13: 46083 | B13: Receita | C13: Dinheiro | D13: Vendas do dia (seg) | E13: 176.88 | G13: =G12+IFERROR(E13,0)-IFERROR(F13,0)
A14: 46084 | B14: Fornecedor | C14: Cárneas | D14: Açougue Boi Forte | F14: 2522.27 | G14: =G13+IFERROR(E14,0)-IFERROR(F14,0)
A15: 46084 | B15: Receita | C15: Cartão crédito | D15: Vendas do dia (ter) | E15: 2272.53 | G15: =G14+IFERROR(E15,0)-IFERROR(F15,0)
A16: 46084 | B16: Receita | C16: Cartão débito | D16: Vendas do dia (ter) | E16: 1111.01 | G16: =G15+IFERROR(E16,0)-IFERROR(F16,0)
A17: 46084 | B17: Receita | C17: PIX | D17: Vendas do dia (ter) | E17: 909.01 | G17: =G16+IFERROR(E17,0)-IFERROR(F17,0)
A18: 46084 | B18: Receita | C18: Dinheiro | D18: Vendas do dia (ter) | E18: 252.5 | G18: =G17+IFERROR(E18,0)-IFERROR(F18,0)
A19: 46084 | B19: Receita | C19: iFood | D19: Repasse semanal iFood | E19: 5946.42 | G19: =G18+IFERROR(E19,0)-IFERROR(F19,0)
A20: 46085 | B20: Despesa fixa | C20: Outras operacionais | D20: Despesas operacionais diversas | F20: 2884.58 | G20: =G19+IFERROR(E20,0)-IFERROR(F20,0)
A21: 46085 | B21: Fornecedor | C21: Hortifruti | D21: Reposição hortifruti | F21: 1005 | G21: =G20+IFERROR(E21,0)-IFERROR(F21,0)
A22: 46085 | B22: Fornecedor | C22: Mercearia | D22: Atacado mercearia | F22: 2003.58 | G22: =G21+IFERROR(E22,0)-IFERROR(F22,0)
A23: 46085 | B23: Receita | C23: Cartão crédito | D23: Vendas do dia (qua) | E23: 2687.82 | G23: =G22+IFERROR(E23,0)-IFERROR(F23,0)
A24: 46085 | B24: Receita | C24: Cartão débito | D24: Vendas do dia (qua) | E24: 1314.05 | G24: =G23+IFERROR(E24,0)-IFERROR(F24,0)
A25: 46085 | B25: Receita | C25: PIX | D25: Vendas do dia (qua) | E25: 1075.13 | G25: =G24+IFERROR(E25,0)-IFERROR(F25,0)
A26: 46085 | B26: Receita | C26: Dinheiro | D26: Vendas do dia (qua) | E26: 298.65 | G26: =G25+IFERROR(E26,0)-IFERROR(F26,0)
A27: 46086 | B27: Despesa fixa | C27: Aluguel | D27: Aluguel mar/2026 | F27: 18000 | G27: =G26+IFERROR(E27,0)-IFERROR(F27,0)
A28: 46086 | B28: Receita | C28: Cartão crédito | D28: Vendas do dia (qui) | E28: 3686.29 | G28: =G27+IFERROR(E28,0)-IFERROR(F28,0)
A29: 46086 | B29: Receita | C29: Cartão débito | D29: Vendas do dia (qui) | E29: 1802.18 | G29: =G28+IFERROR(E29,0)-IFERROR(F29,0)
A30: 46086 | B30: Receita | C30: PIX | D30: Vendas do dia (qui) | E30: 1474.51 | G30: =G29+IFERROR(E30,0)-IFERROR(F30,0)
A31: 46086 | B31: Receita | C31: Dinheiro | D31: Vendas do dia (qui) | E31: 409.59 | G31: =G30+IFERROR(E31,0)-IFERROR(F31,0)
A32: 46087 | B32: Fornecedor | C32: Cárneas | D32: Açougue Boi Forte | F32: 2847.25 | G32: =G31+IFERROR(E32,0)-IFERROR(F32,0)
A33: 46087 | B33: Fornecedor | C33: Laticínios | D33: Laticínios semana | F33: 1199.71 | G33: =G32+IFERROR(E33,0)-IFERROR(F33,0)
A34: 46087 | B34: Receita | C34: Cartão crédito | D34: Vendas do dia (sex) | E34: 5254.44 | G34: =G33+IFERROR(E34,0)-IFERROR(F34,0)
A35: 46087 | B35: Receita | C35: Cartão débito | D35: Vendas do dia (sex) | E35: 2568.84 | G35: =G34+IFERROR(E35,0)-IFERROR(F35,0)
A36: 46087 | B36: Receita | C36: PIX | D36: Vendas do dia (sex) | E36: 2101.78 | G36: =G35+IFERROR(E36,0)-IFERROR(F36,0)
A37: 46087 | B37: Receita | C37: Dinheiro | D37: Vendas do dia (sex) | E37: 583.83 | G37: =G36+IFERROR(E37,0)-IFERROR(F37,0)
A38: 46088 | B38: Despesa variável | C38: Comissão | D38: Comissão garçom (sáb) | F38: 1139.25 | G38: =G37+IFERROR(E38,0)-IFERROR(F38,0)
A39: 46088 | B39: Receita | C39: Cartão crédito | D39: Vendas do dia (sáb) | E39: 6495.61 | G39: =G38+IFERROR(E39,0)-IFERROR(F39,0)
A40: 46088 | B40: Receita | C40: Cartão débito | D40: Vendas do dia (sáb) | E40: 3175.63 | G40: =G39+IFERROR(E40,0)-IFERROR(F40,0)
A41: 46088 | B41: Receita | C41: PIX | D41: Vendas do dia (sáb) | E41: 2598.24 | G41: =G40+IFERROR(E41,0)-IFERROR(F41,0)
A42: 46088 | B42: Receita | C42: Dinheiro | D42: Vendas do dia (sáb) | E42: 721.73 | G42: =G41+IFERROR(E42,0)-IFERROR(F42,0)
A43: 46089 | B43: Despesa variável | C43: Comissão | D43: Comissão garçom (dom) | F43: 988.05 | G43: =G42+IFERROR(E43,0)-IFERROR(F43,0)
A44: 46089 | B44: Receita | C44: Cartão crédito | D44: Vendas do dia (dom) | E44: 6349.32 | G44: =G43+IFERROR(E44,0)-IFERROR(F44,0)
A45: 46089 | B45: Receita | C45: Cartão débito | D45: Vendas do dia (dom) | E45: 3104.11 | G45: =G44+IFERROR(E45,0)-IFERROR(F45,0)
A46: 46089 | B46: Receita | C46: PIX | D46: Vendas do dia (dom) | E46: 2539.73 | G46: =G45+IFERROR(E46,0)-IFERROR(F46,0)
A47: 46089 | B47: Receita | C47: Dinheiro | D47: Vendas do dia (dom) | E47: 705.48 | G47: =G46+IFERROR(E47,0)-IFERROR(F47,0)
A48: 46090 | B48: Fornecedor | C48: Hortifruti | D48: Feira semanal — Ceasa | F48: 1411.45 | G48: =G47+IFERROR(E48,0)-IFERROR(F48,0)
A49: 46090 | B49: Fornecedor | C49: Bebidas | D49: Distribuidora Norte | F49: 4349.23 | G49: =G48+IFERROR(E49,0)-IFERROR(F49,0)
A50: 46090 | B50: Receita | C50: Cartão crédito | D50: Vendas do dia (seg) | E50: 1595.11 | G50: =G49+IFERROR(E50,0)-IFERROR(F50,0)
A51: 46090 | B51: Receita | C51: Cartão débito | D51: Vendas do dia (seg) | E51: 779.83 | G51: =G50+IFERROR(E51,0)-IFERROR(F51,0)
A52: 46090 | B52: Receita | C52: PIX | D52: Vendas do dia (seg) | E52: 638.05 | G52: =G51+IFERROR(E52,0)-IFERROR(F52,0)
A53: 46090 | B53: Receita | C53: Dinheiro | D53: Vendas do dia (seg) | E53: 177.23 | G53: =G52+IFERROR(E53,0)-IFERROR(F53,0)
A54: 46091 | B54: Fornecedor | C54: Cárneas | D54: Açougue Boi Forte | F54: 2824.28 | G54: =G53+IFERROR(E54,0)-IFERROR(F54,0)
A55: 46091 | B55: Receita | C55: Cartão crédito | D55: Vendas do dia (ter) | E55: 2221.77 | G55: =G54+IFERROR(E55,0)-IFERROR(F55,0)
A56: 46091 | B56: Receita | C56: Cartão débito | D56: Vendas do dia (ter) | E56: 1086.2 | G56: =G55+IFERROR(E56,0)-IFERROR(F56,0)
A57: 46091 | B57: Receita | C57: PIX | D57: Vendas do dia (ter) | E57: 888.71 | G57: =G56+IFERROR(E57,0)-IFERROR(F57,0)
A58: 46091 | B58: Receita | C58: Dinheiro | D58: Vendas do dia (ter) | E58: 246.86 | G58: =G57+IFERROR(E58,0)-IFERROR(F58,0)
A59: 46091 | B59: Receita | C59: iFood | D59: Repasse semanal iFood | E59: 6510.71 | G59: =G58+IFERROR(E59,0)-IFERROR(F59,0)
A60: 46091 | B60: Sócios | C60: Pró-labore | D60: Sócio A — mar/2026 | F60: 8000 | G60: =G59+IFERROR(E60,0)-IFERROR(F60,0)
A61: 46091 | B61: Sócios | C61: Pró-labore | D61: Sócio B — mar/2026 | F61: 8000 | G61: =G60+IFERROR(E61,0)-IFERROR(F61,0)
A62: 46092 | B62: Despesa fixa | C62: Outras operacionais | D62: Despesas operacionais diversas | F62: 1666.93 | G62: =G61+IFERROR(E62,0)-IFERROR(F62,0)
A63: 46092 | B63: Fornecedor | C63: Hortifruti | D63: Reposição hortifruti | F63: 700.23 | G63: =G62+IFERROR(E63,0)-IFERROR(F63,0)
A64: 46092 | B64: Fornecedor | C64: Mercearia | D64: Atacado mercearia | F64: 2317 | G64: =G63+IFERROR(E64,0)-IFERROR(F64,0)
A65: 46092 | B65: Receita | C65: Cartão crédito | D65: Vendas do dia (qua) | E65: 2048.88 | G65: =G64+IFERROR(E65,0)-IFERROR(F65,0)
A66: 46092 | B66: Receita | C66: Cartão débito | D66: Vendas do dia (qua) | E66: 1001.68 | G66: =G65+IFERROR(E66,0)-IFERROR(F66,0)
A67: 46092 | B67: Receita | C67: PIX | D67: Vendas do dia (qua) | E67: 819.55 | G67: =G66+IFERROR(E67,0)-IFERROR(F67,0)
A68: 46092 | B68: Receita | C68: Dinheiro | D68: Vendas do dia (qua) | E68: 227.65 | G68: =G67+IFERROR(E68,0)-IFERROR(F68,0)
A69: 46093 | B69: Despesa fixa | C69: Energia | D69: Enel — mar/2026 | F69: 3840 | G69: =G68+IFERROR(E69,0)-IFERROR(F69,0)
A70: 46093 | B70: Receita | C70: Cartão crédito | D70: Vendas do dia (qui) | E70: 3148.69 | G70: =G69+IFERROR(E70,0)-IFERROR(F70,0)
A71: 46093 | B71: Receita | C71: Cartão débito | D71: Vendas do dia (qui) | E71: 1539.36 | G71: =G70+IFERROR(E71,0)-IFERROR(F71,0)
A72: 46093 | B72: Receita | C72: PIX | D72: Vendas do dia (qui) | E72: 1259.48 | G72: =G71+IFERROR(E72,0)-IFERROR(F72,0)
A73: 46093 | B73: Receita | C73: Dinheiro | D73: Vendas do dia (qui) | E73: 349.85 | G73: =G72+IFERROR(E73,0)-IFERROR(F73,0)
A74: 46094 | B74: Despesa fixa | C74: Gás | D74: Recarga GLP | F74: 980 | G74: =G73+IFERROR(E74,0)-IFERROR(F74,0)
A75: 46094 | B75: Fornecedor | C75: Cárneas | D75: Açougue Boi Forte | F75: 2588.99 | G75: =G74+IFERROR(E75,0)-IFERROR(F75,0)
A76: 46094 | B76: Fornecedor | C76: Laticínios | D76: Laticínios semana | F76: 1134.41 | G76: =G75+IFERROR(E76,0)-IFERROR(F76,0)
A77: 46094 | B77: Receita | C77: Cartão crédito | D77: Vendas do dia (sex) | E77: 4927.34 | G77: =G76+IFERROR(E77,0)-IFERROR(F77,0)
A78: 46094 | B78: Receita | C78: Cartão débito | D78: Vendas do dia (sex) | E78: 2408.92 | G78: =G77+IFERROR(E78,0)-IFERROR(F78,0)
A79: 46094 | B79: Receita | C79: PIX | D79: Vendas do dia (sex) | E79: 1970.94 | G79: =G78+IFERROR(E79,0)-IFERROR(F79,0)
A80: 46094 | B80: Receita | C80: Dinheiro | D80: Vendas do dia (sex) | E80: 547.48 | G80: =G79+IFERROR(E80,0)-IFERROR(F80,0)
A81: 46095 | B81: Despesa variável | C81: Comissão | D81: Comissão garçom (sáb) | F81: 1315.06 | G81: =G80+IFERROR(E81,0)-IFERROR(F81,0)
A82: 46095 | B82: Fornecedor | C82: Descartáveis | D82: Embalagens Sul | F82: 1420 | G82: =G81+IFERROR(E82,0)-IFERROR(F82,0)
A83: 46095 | B83: Fornecedor | C83: Descartáveis | D83: Embalagens Sul | F83: 1420 | G83: =G82+IFERROR(E83,0)-IFERROR(F83,0)
A84: 46095 | B84: Receita | C84: Cartão crédito | D84: Vendas do dia (sáb) | E84: 7526.12 | G84: =G83+IFERROR(E84,0)-IFERROR(F84,0)
A85: 46095 | B85: Receita | C85: Cartão débito | D85: Vendas do dia (sáb) | E85: 3679.44 | G85: =G84+IFERROR(E85,0)-IFERROR(F85,0)
A86: 46095 | B86: Receita | C86: PIX | D86: Vendas do dia (sáb) | E86: 3010.45 | G86: =G85+IFERROR(E86,0)-IFERROR(F86,0)
A87: 46095 | B87: Receita | C87: Dinheiro | D87: Vendas do dia (sáb) | E87: 836.24 | G87: =G86+IFERROR(E87,0)-IFERROR(F87,0)
A88: 46096 | B88: Despesa fixa | C88: Folha | D88: Folha 1ª quinzena | F88: 26180 | G88: =G87+IFERROR(E88,0)-IFERROR(F88,0)
A89: 46096 | B89: Despesa variável | C89: Comissão | D89: Comissão garçom (dom) | F89: 1188.4 | G89: =G88+IFERROR(E89,0)-IFERROR(F89,0)
A90: 46096 | B90: Receita | C90: Cartão crédito | D90: Vendas do dia (dom) | E90: 5895.99 | G90: =G89+IFERROR(E90,0)-IFERROR(F90,0)
A91: 46096 | B91: Receita | C91: Cartão débito | D91: Vendas do dia (dom) | E91: 2882.48 | G91: =G90+IFERROR(E91,0)-IFERROR(F91,0)
A92: 46096 | B92: Receita | C92: PIX | D92: Vendas do dia (dom) | E92: 2358.4 | G92: =G91+IFERROR(E92,0)-IFERROR(F92,0)
A93: 46096 | B93: Receita | C93: Dinheiro | D93: Vendas do dia (dom) | E93: 655.11 | G93: =G92+IFERROR(E93,0)-IFERROR(F93,0)
A94: 46097 | B94: Fornecedor | C94: Hortifruti | D94: Feira semanal — Ceasa | F94: 1107.79 | G94: =G93+IFERROR(E94,0)-IFERROR(F94,0)
A95: 46097 | B95: Fornecedor | C95: Bebidas | D95: Distribuidora Norte | F95: 4365.25 | G95: =G94+IFERROR(E95,0)-IFERROR(F95,0)
A96: 46097 | B96: Receita | C96: Cartão crédito | D96: Vendas do dia (seg) | E96: 1972.75 | G96: =G95+IFERROR(E96,0)-IFERROR(F96,0)
A97: 46097 | B97: Receita | C97: Cartão débito | D97: Vendas do dia (seg) | E97: 964.46 | G97: =G96+IFERROR(E97,0)-IFERROR(F97,0)
A98: 46097 | B98: Receita | C98: PIX | D98: Vendas do dia (seg) | E98: 789.1 | G98: =G97+IFERROR(E98,0)-IFERROR(F98,0)
A99: 46097 | B99: Receita | C99: Dinheiro | D99: Vendas do dia (seg) | E99: 219.19 | G99: =G98+IFERROR(E99,0)-IFERROR(F99,0)
A100: 46098 | B100: Despesa variável | C100: Marketing | D100: Tráfego pago — Meta Ads | F100: 1200 | G100: =G99+IFERROR(E100,0)-IFERROR(F100,0)
...

Sheet Resumo Mensal
A1: Mês | B1: Receita Bruta R$ | C1: Total Despesas R$ | D1: Saldo Mensal R$
A2: Março/2026 | B2: =SUMIFS('Fluxo Diário'!E2:E568,'Fluxo Diário'!A2:A568,">="&DATE(2026,3,1),'Fluxo Diário'!A2:A568,"<="&DATE(2026,3,31)) | C2: =SUMIFS('Fluxo Diário'!F2:F568,'Fluxo Diário'!A2:A568,">="&DATE(2026,3,1),'Fluxo Diário'!A2:A568,"<="&DATE(2026,3,31)) | D2: =B2-C2
A3: Abril/2026 | B3: =SUMIFS('Fluxo Diário'!E2:E568,'Fluxo Diário'!A2:A568,">="&DATE(2026,4,1),'Fluxo Diário'!A2:A568,"<="&DATE(2026,4,30)) | C3: =SUMIFS('Fluxo Diário'!F2:F568,'Fluxo Diário'!A2:A568,">="&DATE(2026,4,1),'Fluxo Diário'!A2:A568,"<="&DATE(2026,4,30)) | D3: =B3-C3
A4: Maio/2026 | B4: =SUMIFS('Fluxo Diário'!E2:E568,'Fluxo Diário'!A2:A568,">="&DATE(2026,5,1),'Fluxo Diário'!A2:A568,"<="&DATE(2026,5,31)) | C4: =SUMIFS('Fluxo Diário'!F2:F568,'Fluxo Diário'!A2:A568,">="&DATE(2026,5,1),'Fluxo Diário'!A2:A568,"<="&DATE(2026,5,31)) | D4: =B4-C4
A5: TOTAL 3M | B5: =SUM(B2:B4) | C5: =SUM(C2:C4) | D5: =SUM(D2:D4)
