Workbook

Sheet DRE Cascata G4
A1: # | B1: Conta | C1: Mar/2026 | D1: Abr/2026 | E1: Mai/2026 | F1: Média 3M | G1: % vertical
A2: 1 | B2: (=) Receita Bruta | C2: 261840 | D2: 288420 | E2: 273180 | F2: =AVERAGE(C2:E2) | G2: =IFERROR(F2/$F$2,0)
A3: 2 | B3: (−) Deduções (impostos sobre venda + descontos) | C3: -15710 | D3: -17305 | E3: -16391 | F3: =AVERAGE(C3:E3) | G3: =IFERROR(F3/$F$2,0)
A4: 3 | B4: (=) Receita Líquida | C4: =C2+C3 | D4: =D2+D3 | E4: =E2+E3 | F4: =AVERAGE(C4:E4) | G4: =IFERROR(F4/$F$2,0)
A5: 4 | B5: (−) CMV (alimentos + bebidas + descartáveis) | C5: -83789 | D5: -91420 | E5: -86840 | F5: =AVERAGE(C5:E5) | G5: =IFERROR(F5/$F$2,0)
A6: 5 | B6: (=) Lucro Bruto | C6: =C4+C5 | D6: =D4+D5 | E6: =E4+E5 | F6: =AVERAGE(C6:E6) | G6: =IFERROR(F6/$F$2,0)
A7: 6 | B7: (−) Despesas Variáveis | C7: =C8+C9+C10+C11 | D7: =D8+D9+D10+D11 | E7: =E8+E9+E10+E11 | F7: =AVERAGE(C7:E7) | G7: =IFERROR(F7/$F$2,0)
A8: 6.1 | B8: Taxa cartão (~3% receita) | C8: -7855 | D8: -8653 | E8: -8195 | F8: =AVERAGE(C8:E8) | G8: =IFERROR(F8/$F$2,0)
A9: 6.2 | B9: Comissão garçom (10% receita salão) | C9: -10470 | D9: -11537 | E9: -10927 | F9: =AVERAGE(C9:E9) | G9: =IFERROR(F9/$F$2,0)
A10: 6.3 | B10: Taxa iFood/delivery | C10: -2620 | D10: -2880 | E10: -2730 | F10: =AVERAGE(C10:E10) | G10: =IFERROR(F10/$F$2,0)
A11: 6.4 | B11: Marketing variável (% sobre receita) | C11: -1235 | D11: -1770 | E11: -1658 | F11: =AVERAGE(C11:E11) | G11: =IFERROR(F11/$F$2,0)
A12: 7 | B12: (=) Margem de Contribuição | C12: =C6+C7 | D12: =D6+D7 | E12: =E6+E7 | F12: =AVERAGE(C12:E12) | G12: =IFERROR(F12/$F$2,0)
A13: 8 | B13: (−) Despesas Operacionais Fixas | C13: =C14+C15+C16+C17+C18+C19+C20+C21+C22+C23 | D13: =D14+D15+D16+D17+D18+D19+D20+D21+D22+D23 | E13: =E14+E15+E16+E17+E18+E19+E20+E21+E22+E23 | F13: =AVERAGE(C13:E13) | G13: =IFERROR(F13/$F$2,0)
A14: 8.1 | B14: Folha (cozinha + salão + encargos) | C14: -52600 | D14: -53180 | E14: -52840 | F14: =AVERAGE(C14:E14) | G14: =IFERROR(F14/$F$2,0)
A15: 8.2 | B15: Aluguel | C15: -18000 | D15: -18000 | E15: -18000 | F15: =AVERAGE(C15:E15) | G15: =IFERROR(F15/$F$2,0)
A16: 8.3 | B16: Energia (Enel) | C16: -3840 | D16: -3920 | E16: -3880 | F16: =AVERAGE(C16:E16) | G16: =IFERROR(F16/$F$2,0)
A17: 8.4 | B17: Água (Cagece) | C17: -1180 | D17: -1220 | E17: -1190 | F17: =AVERAGE(C17:E17) | G17: =IFERROR(F17/$F$2,0)
A18: 8.5 | B18: Gás (GLP) | C18: -980 | D18: -1020 | E18: -990 | F18: =AVERAGE(C18:E18) | G18: =IFERROR(F18/$F$2,0)
A19: 8.6 | B19: Internet + telefonia | C19: -480 | D19: -480 | E19: -480 | F19: =AVERAGE(C19:E19) | G19: =IFERROR(F19/$F$2,0)
A20: 8.7 | B20: Contabilidade | C20: -1450 | D20: -1450 | E20: -1450 | F20: =AVERAGE(C20:E20) | G20: =IFERROR(F20/$F$2,0)
A21: 8.8 | B21: Software (PDV + gestão + ERP) | C21: -890 | D21: -890 | E21: -890 | F21: =AVERAGE(C21:E21) | G21: =IFERROR(F21/$F$2,0)
A22: 8.9 | B22: Pró-labore sócios (A + B) | C22: -16000 | D22: -16000 | E22: -16000 | F22: =AVERAGE(C22:E22) | G22: =IFERROR(F22/$F$2,0)
A23: 8.10 | B23: Outras despesas operacionais | C23: -12470 | D23: -12260 | E23: -12430 | F23: =AVERAGE(C23:E23) | G23: =IFERROR(F23/$F$2,0)
A24: 9 | B24: (=) EBITDA | C24: =C12+C13 | D24: =D12+D13 | E24: =E12+E13 | F24: =AVERAGE(C24:E24) | G24: =IFERROR(F24/$F$2,0)
A25: 10 | B25: (−) Depreciação (equip. cozinha + mobiliário) | C25: -2400 | D25: -2400 | E25: -2400 | F25: =AVERAGE(C25:E25) | G25: =IFERROR(F25/$F$2,0)
A26: 11 | B26: (=) EBIT / Resultado Operacional | C26: =C24+C25 | D26: =D24+D25 | E26: =E24+E25 | F26: =AVERAGE(C26:E26) | G26: =IFERROR(F26/$F$2,0)
A27: 12 | B27: (−) Imposto sobre lucro (no Simples já está no item 2) | C27: 0 | D27: 0 | E27: 0 | F27: =AVERAGE(C27:E27) | G27: =IFERROR(F27/$F$2,0)
A28: 13 | B28: (=) Lucro Líquido | C28: =C26+C27 | D28: =D26+D27 | E28: =E26+E27 | F28: =AVERAGE(C28:E28) | G28: =IFERROR(F28/$F$2,0)

Sheet Indicadores
A1: Indicador | B1: Valor | C1: Benchmark mercado | D1: Status
A2: Margem Bruta | B2: ='DRE Cascata G4'!F6/'DRE Cascata G4'!F2 | C2: 60–70% (casual food) | D2: OK
A3: Margem de Contribuição | B3: ='DRE Cascata G4'!F12/'DRE Cascata G4'!F2 | C3: 50–60% | D3: OK
A4: Margem EBITDA | B4: ='DRE Cascata G4'!F24/'DRE Cascata G4'!F2 | C4: 12–18% | D4: OK
A5: Margem Líquida | B5: ='DRE Cascata G4'!F28/'DRE Cascata G4'!F2 | C5: 8–15% | D5: Checar se faltou despesa
A6: Ponto de equilíbrio (R$/mês) | B6: =-'DRE Cascata G4'!F13/('DRE Cascata G4'!F12/'DRE Cascata G4'!F2) | C6: — | D6: Receita atual ~30% acima
