Workbook

Sheet Premissas
A1: Cenário | B1: Distribuição Ano 1 (R$/mês) | C1: Crescimento Real a.a. | D1: Inflação a.a. | E1: Crescimento Nominal a.a. | F1: TMA Nominal a.a. | G1: TMA Nominal a.m. | H1: Investimento Inicial R$ | I1: Horizonte (meses)
A2: Estresse | B2: 5000 | C2: 0 | D2: 0.04 | E2: =(1+C2)*(1+D2)-1 | F2: 0.22 | G2: =(1+F2)^(1/12)-1 | H2: 180000 | I2: 60
A3: Base | B3: 7000 | C3: 0.03 | D3: 0.04 | E3: =(1+C3)*(1+D3)-1 | F3: 0.19 | G3: =(1+F3)^(1/12)-1 | H3: 180000 | I3: 60
A4: Otimista | B4: 9000 | C4: 0.05 | D4: 0.04 | E4: =(1+C4)*(1+D4)-1 | F4: 0.17 | G4: =(1+F4)^(1/12)-1 | H4: 180000 | I4: 60

Sheet DCF Cálculo
A1: Mês | B1: Distribuição Nominal R$ | C1: Fator Desconto | D1: VP do Fluxo R$ | E1: VP Acumulado R$
A2: 0 | B2: =-Premissas!H3 | C2: 1 | D2: =B2*C2 | E2: =D2
A3: 1 | B3: =Premissas!B3*((1+Premissas!E3)^INT((1-1)/12)) | C3: =1/((1+Premissas!G3)^1) | D3: =B3*C3 | E3: =E2+D3
A4: 2 | B4: =Premissas!B3*((1+Premissas!E3)^INT((2-1)/12)) | C4: =1/((1+Premissas!G3)^2) | D4: =B4*C4 | E4: =E3+D4
A5: 3 | B5: =Premissas!B3*((1+Premissas!E3)^INT((3-1)/12)) | C5: =1/((1+Premissas!G3)^3) | D5: =B5*C5 | E5: =E4+D5
A6: 4 | B6: =Premissas!B3*((1+Premissas!E3)^INT((4-1)/12)) | C6: =1/((1+Premissas!G3)^4) | D6: =B6*C6 | E6: =E5+D6
A7: 5 | B7: =Premissas!B3*((1+Premissas!E3)^INT((5-1)/12)) | C7: =1/((1+Premissas!G3)^5) | D7: =B7*C7 | E7: =E6+D7
A8: 6 | B8: =Premissas!B3*((1+Premissas!E3)^INT((6-1)/12)) | C8: =1/((1+Premissas!G3)^6) | D8: =B8*C8 | E8: =E7+D8
A9: 7 | B9: =Premissas!B3*((1+Premissas!E3)^INT((7-1)/12)) | C9: =1/((1+Premissas!G3)^7) | D9: =B9*C9 | E9: =E8+D9
A10: 8 | B10: =Premissas!B3*((1+Premissas!E3)^INT((8-1)/12)) | C10: =1/((1+Premissas!G3)^8) | D10: =B10*C10 | E10: =E9+D10
A11: 9 | B11: =Premissas!B3*((1+Premissas!E3)^INT((9-1)/12)) | C11: =1/((1+Premissas!G3)^9) | D11: =B11*C11 | E11: =E10+D11
A12: 10 | B12: =Premissas!B3*((1+Premissas!E3)^INT((10-1)/12)) | C12: =1/((1+Premissas!G3)^10) | D12: =B12*C12 | E12: =E11+D12
A13: 11 | B13: =Premissas!B3*((1+Premissas!E3)^INT((11-1)/12)) | C13: =1/((1+Premissas!G3)^11) | D13: =B13*C13 | E13: =E12+D13
A14: 12 | B14: =Premissas!B3*((1+Premissas!E3)^INT((12-1)/12)) | C14: =1/((1+Premissas!G3)^12) | D14: =B14*C14 | E14: =E13+D14
A15: 13 | B15: =Premissas!B3*((1+Premissas!E3)^INT((13-1)/12)) | C15: =1/((1+Premissas!G3)^13) | D15: =B15*C15 | E15: =E14+D15
A16: 14 | B16: =Premissas!B3*((1+Premissas!E3)^INT((14-1)/12)) | C16: =1/((1+Premissas!G3)^14) | D16: =B16*C16 | E16: =E15+D16
A17: 15 | B17: =Premissas!B3*((1+Premissas!E3)^INT((15-1)/12)) | C17: =1/((1+Premissas!G3)^15) | D17: =B17*C17 | E17: =E16+D17
A18: 16 | B18: =Premissas!B3*((1+Premissas!E3)^INT((16-1)/12)) | C18: =1/((1+Premissas!G3)^16) | D18: =B18*C18 | E18: =E17+D18
A19: 17 | B19: =Premissas!B3*((1+Premissas!E3)^INT((17-1)/12)) | C19: =1/((1+Premissas!G3)^17) | D19: =B19*C19 | E19: =E18+D19
A20: 18 | B20: =Premissas!B3*((1+Premissas!E3)^INT((18-1)/12)) | C20: =1/((1+Premissas!G3)^18) | D20: =B20*C20 | E20: =E19+D20
A21: 19 | B21: =Premissas!B3*((1+Premissas!E3)^INT((19-1)/12)) | C21: =1/((1+Premissas!G3)^19) | D21: =B21*C21 | E21: =E20+D21
A22: 20 | B22: =Premissas!B3*((1+Premissas!E3)^INT((20-1)/12)) | C22: =1/((1+Premissas!G3)^20) | D22: =B22*C22 | E22: =E21+D22
A23: 21 | B23: =Premissas!B3*((1+Premissas!E3)^INT((21-1)/12)) | C23: =1/((1+Premissas!G3)^21) | D23: =B23*C23 | E23: =E22+D23
A24: 22 | B24: =Premissas!B3*((1+Premissas!E3)^INT((22-1)/12)) | C24: =1/((1+Premissas!G3)^22) | D24: =B24*C24 | E24: =E23+D24
A25: 23 | B25: =Premissas!B3*((1+Premissas!E3)^INT((23-1)/12)) | C25: =1/((1+Premissas!G3)^23) | D25: =B25*C25 | E25: =E24+D25
A26: 24 | B26: =Premissas!B3*((1+Premissas!E3)^INT((24-1)/12)) | C26: =1/((1+Premissas!G3)^24) | D26: =B26*C26 | E26: =E25+D26
A27: 25 | B27: =Premissas!B3*((1+Premissas!E3)^INT((25-1)/12)) | C27: =1/((1+Premissas!G3)^25) | D27: =B27*C27 | E27: =E26+D27
A28: 26 | B28: =Premissas!B3*((1+Premissas!E3)^INT((26-1)/12)) | C28: =1/((1+Premissas!G3)^26) | D28: =B28*C28 | E28: =E27+D28
A29: 27 | B29: =Premissas!B3*((1+Premissas!E3)^INT((27-1)/12)) | C29: =1/((1+Premissas!G3)^27) | D29: =B29*C29 | E29: =E28+D29
A30: 28 | B30: =Premissas!B3*((1+Premissas!E3)^INT((28-1)/12)) | C30: =1/((1+Premissas!G3)^28) | D30: =B30*C30 | E30: =E29+D30
A31: 29 | B31: =Premissas!B3*((1+Premissas!E3)^INT((29-1)/12)) | C31: =1/((1+Premissas!G3)^29) | D31: =B31*C31 | E31: =E30+D31
A32: 30 | B32: =Premissas!B3*((1+Premissas!E3)^INT((30-1)/12)) | C32: =1/((1+Premissas!G3)^30) | D32: =B32*C32 | E32: =E31+D32
A33: 31 | B33: =Premissas!B3*((1+Premissas!E3)^INT((31-1)/12)) | C33: =1/((1+Premissas!G3)^31) | D33: =B33*C33 | E33: =E32+D33
A34: 32 | B34: =Premissas!B3*((1+Premissas!E3)^INT((32-1)/12)) | C34: =1/((1+Premissas!G3)^32) | D34: =B34*C34 | E34: =E33+D34
A35: 33 | B35: =Premissas!B3*((1+Premissas!E3)^INT((33-1)/12)) | C35: =1/((1+Premissas!G3)^33) | D35: =B35*C35 | E35: =E34+D35
A36: 34 | B36: =Premissas!B3*((1+Premissas!E3)^INT((34-1)/12)) | C36: =1/((1+Premissas!G3)^34) | D36: =B36*C36 | E36: =E35+D36
A37: 35 | B37: =Premissas!B3*((1+Premissas!E3)^INT((35-1)/12)) | C37: =1/((1+Premissas!G3)^35) | D37: =B37*C37 | E37: =E36+D37
A38: 36 | B38: =Premissas!B3*((1+Premissas!E3)^INT((36-1)/12)) | C38: =1/((1+Premissas!G3)^36) | D38: =B38*C38 | E38: =E37+D38
A39: 37 | B39: =Premissas!B3*((1+Premissas!E3)^INT((37-1)/12)) | C39: =1/((1+Premissas!G3)^37) | D39: =B39*C39 | E39: =E38+D39
A40: 38 | B40: =Premissas!B3*((1+Premissas!E3)^INT((38-1)/12)) | C40: =1/((1+Premissas!G3)^38) | D40: =B40*C40 | E40: =E39+D40
A41: 39 | B41: =Premissas!B3*((1+Premissas!E3)^INT((39-1)/12)) | C41: =1/((1+Premissas!G3)^39) | D41: =B41*C41 | E41: =E40+D41
A42: 40 | B42: =Premissas!B3*((1+Premissas!E3)^INT((40-1)/12)) | C42: =1/((1+Premissas!G3)^40) | D42: =B42*C42 | E42: =E41+D42
A43: 41 | B43: =Premissas!B3*((1+Premissas!E3)^INT((41-1)/12)) | C43: =1/((1+Premissas!G3)^41) | D43: =B43*C43 | E43: =E42+D43
A44: 42 | B44: =Premissas!B3*((1+Premissas!E3)^INT((42-1)/12)) | C44: =1/((1+Premissas!G3)^42) | D44: =B44*C44 | E44: =E43+D44
A45: 43 | B45: =Premissas!B3*((1+Premissas!E3)^INT((43-1)/12)) | C45: =1/((1+Premissas!G3)^43) | D45: =B45*C45 | E45: =E44+D45
A46: 44 | B46: =Premissas!B3*((1+Premissas!E3)^INT((44-1)/12)) | C46: =1/((1+Premissas!G3)^44) | D46: =B46*C46 | E46: =E45+D46
A47: 45 | B47: =Premissas!B3*((1+Premissas!E3)^INT((45-1)/12)) | C47: =1/((1+Premissas!G3)^45) | D47: =B47*C47 | E47: =E46+D47
A48: 46 | B48: =Premissas!B3*((1+Premissas!E3)^INT((46-1)/12)) | C48: =1/((1+Premissas!G3)^46) | D48: =B48*C48 | E48: =E47+D48
A49: 47 | B49: =Premissas!B3*((1+Premissas!E3)^INT((47-1)/12)) | C49: =1/((1+Premissas!G3)^47) | D49: =B49*C49 | E49: =E48+D49
A50: 48 | B50: =Premissas!B3*((1+Premissas!E3)^INT((48-1)/12)) | C50: =1/((1+Premissas!G3)^48) | D50: =B50*C50 | E50: =E49+D50
A51: 49 | B51: =Premissas!B3*((1+Premissas!E3)^INT((49-1)/12)) | C51: =1/((1+Premissas!G3)^49) | D51: =B51*C51 | E51: =E50+D51
A52: 50 | B52: =Premissas!B3*((1+Premissas!E3)^INT((50-1)/12)) | C52: =1/((1+Premissas!G3)^50) | D52: =B52*C52 | E52: =E51+D52
A53: 51 | B53: =Premissas!B3*((1+Premissas!E3)^INT((51-1)/12)) | C53: =1/((1+Premissas!G3)^51) | D53: =B53*C53 | E53: =E52+D53
A54: 52 | B54: =Premissas!B3*((1+Premissas!E3)^INT((52-1)/12)) | C54: =1/((1+Premissas!G3)^52) | D54: =B54*C54 | E54: =E53+D54
A55: 53 | B55: =Premissas!B3*((1+Premissas!E3)^INT((53-1)/12)) | C55: =1/((1+Premissas!G3)^53) | D55: =B55*C55 | E55: =E54+D55
A56: 54 | B56: =Premissas!B3*((1+Premissas!E3)^INT((54-1)/12)) | C56: =1/((1+Premissas!G3)^54) | D56: =B56*C56 | E56: =E55+D56
A57: 55 | B57: =Premissas!B3*((1+Premissas!E3)^INT((55-1)/12)) | C57: =1/((1+Premissas!G3)^55) | D57: =B57*C57 | E57: =E56+D57
A58: 56 | B58: =Premissas!B3*((1+Premissas!E3)^INT((56-1)/12)) | C58: =1/((1+Premissas!G3)^56) | D58: =B58*C58 | E58: =E57+D58
A59: 57 | B59: =Premissas!B3*((1+Premissas!E3)^INT((57-1)/12)) | C59: =1/((1+Premissas!G3)^57) | D59: =B59*C59 | E59: =E58+D59
A60: 58 | B60: =Premissas!B3*((1+Premissas!E3)^INT((58-1)/12)) | C60: =1/((1+Premissas!G3)^58) | D60: =B60*C60 | E60: =E59+D60
A61: 59 | B61: =Premissas!B3*((1+Premissas!E3)^INT((59-1)/12)) | C61: =1/((1+Premissas!G3)^59) | D61: =B61*C61 | E61: =E60+D61
A62: 60 | B62: =Premissas!B3*((1+Premissas!E3)^INT((60-1)/12)) | C62: =1/((1+Premissas!G3)^60) | D62: =B62*C62 | E62: =E61+D62
A64: Indicadores (Cenário Base)
A65: VPL (Valor Presente Líquido) | B65: =SUM(D2:D62)
A66: TIR Mensal | B66: =IRR(B2:B62)
A67: TIR Anual Equivalente | B67: =(1+B66)^12-1
A68: Payback Descontado (mês em que VP acumulado vira positivo) | B68: =MATCH(TRUE,INDEX(E3:E62>0,0),0)
A69: Lucro Total Nominal (60 meses) | B69: =SUM(B3:B62)

Sheet Sensibilidade
A1: Sensibilidade VPL (Cenário Base) — TMA × Crescimento Real
A2: Variando TMA nas linhas, Crescimento Real nas colunas
A4: TMA \ Cresc.Real | B4: -0.02 | C4: 0 | D4: 0.03 | E4: 0.05 | F4: 0.08
A5: 0.13 | B5: 143402.58 | C5: 155477.83 | D5: 174479 | E5: 187758.98 | F5: 208633.27
A6: 0.16 | B6: 124494.3 | C6: 135534.21 | D6: 152894.22 | E6: 165019.17 | F6: 184065.73
A7: 0.19 | B7: 107520 | C7: 117644.12 | D7: 133553.28 | E7: 144657.64 | F7: 162089.98
A8: 0.22 | B8: 92225.24 | C8: 101536.37 | D8: 116158.17 | E8: 126357.4 | F8: 142358.83
A9: 0.25 | B9: 78395.36 | C9: 86982.21 | D9: 100457.74 | E9: 109851.43 | F9: 124579.99
A10: 0.3 | B10: 58118.82 | C10: 65664.41 | D10: 77493.13 | E10: 85730.28 | F10: 98632.44
A11: 0.35 | B11: 40731.43 | C11: 47406.03 | D11: 57858.37 | E11: 65129.68 | F11: 76507.8
A12: 0.47 | B12: 7850.84 | C12: 12943.91 | D12: 20900.43 | E12: 26422.64 | F12: 35044.22
A15: Leitura
A16: Verde = VPL > 0 (investimento vale a pena nessa combinação).
A17: Vermelho = VPL < 0 (não vale a pena).
A18: TMA de equilíbrio ≈ TIR. No cenário base (Cresc Real 3%, Infl 4%, Dist R$ 7k/mês), TIR ~47% a.a.
