Workbook

Sheet Legend
A1: Modelo de Acompanhamento Trimestral · versão herdada
A2: Última edição: Marcos S. · Q2/2026 · Marcos saiu da equipe em Jul/2026
A4: Estrutura do modelo
A5: Aba 'Sazonal' | B5: Fatores de sazonalidade trimestrais. NUNCA mudar sem alinhar com finanças.
A6: Aba 'Receita' | B6: Receita bruta por trimestre. Q1-Q2 preenchidos. Q3-Q4 vazios (você preenche).
A7: Aba 'Custos' | B7: Custos por trimestre. Salários + Operacional + Marketing.
A8: Aba 'DRE' | B8: Puxa Receita e Custos, aplica sazonalidade, entrega margem líquida.
A9: Aba 'KPIs' | B9: Indicadores derivados do DRE — ticket médio, custo/entrega, margem %.
A12: Código de cor
A13: Azul (0,0,255) | B13: Input hardcoded — você edita direto
A14: Preto | B14: Fórmula da mesma aba
A15: Verde (0,128,0) | B15: Fórmula que puxa de outra aba
A16: Amarelo fill | B16: Premissa-chave — revise a cada trimestre
A19: Notas do Marcos (do que ele deixou)
A20: 1. A sazonalidade é aplicada ANTES do cálculo de margem — não depois. Se inverter, distorce Q1.
A21: 2. Custo de salário sobe 8% em Q1 (dissídio). Isso está hardcoded em 'Custos'!C4.
A22: 3. Marketing é sazonal: sobe 40% em Q4 (Black Friday). Está no fator de 'Sazonal'!C5.
A23: 4. KPI 'custo por entrega' usa TOTAL de entregas do trimestre, não a média mensal.
A24: 5. Se receita cair >20% num trimestre, o modelo 'trava' custos no nível anterior (proteção manual).

Sheet Sazonal
A1: Fatores de Sazonalidade
A3: Trimestre | B3: Receita | C3: Custo salário | D3: Custo operacional | E3: Custo marketing
A4: Q1 | B4: 0.88 | C4: 1.08 | D4: 1 | E4: 0.85
A5: Q2 | B5: 1.02 | C5: 1 | D5: 1 | E5: 0.95
A6: Q3 | B6: 0.95 | C6: 1 | D6: 1 | E6: 0.9
A7: Q4 | B7: 1.15 | C7: 1 | D7: 1.05 | E7: 1.4
A9: Fatores fictícios · revisar a cada ano

Sheet Receita
A1: Receita Trimestral 2026
A3: Segmento | B3: Q1 | C3: Q2 | D3: Q3 | E3: Q4 | F3: Total ano
A4: Serviços recorrentes | B4: 420000 | C4: 465000 | F4: =SUM(B4:E4)
A5: Projetos pontuais | B5: 180000 | C5: 210000 | F5: =SUM(B5:E5)
A6: Consultoria estratégica | B6: 95000 | C6: 110000 | F6: =SUM(B6:E6)
A7: Treinamentos | B7: 60000 | C7: 72000 | F7: =SUM(B7:E7)
A8: Total | B8: =SUM(B4:B7) | C8: =SUM(C4:C7) | D8: =SUM(D4:D7) | E8: =SUM(E4:E7) | F8: =SUM(F4:F7)
A10: Legenda: azul = valor real preenchido · amarelo = a preencher (Q3-Q4)

Sheet Custos
A1: Custos Trimestrais 2026
A3: Categoria | B3: Q1 | C3: Q2 | D3: Q3 | E3: Q4 | F3: Total ano
A4: Salários (com encargos) | B4: 285000 | C4: 265000 | F4: =SUM(B4:E4)
A5: Operacional (aluguel/luz/software) | B5: 78000 | C5: 78000 | F5: =SUM(B5:E5)
A6: Marketing | B6: 42000 | C6: 48000 | F6: =SUM(B6:E6)
A7: Impostos + taxas | B7: 68000 | C7: 72000 | F7: =SUM(B7:E7)
A8: Total | B8: =SUM(B4:B7) | C8: =SUM(C4:C7) | D8: =SUM(D4:D7) | E8: =SUM(E4:E7) | F8: =SUM(F4:F7)
A10: Legenda: azul = hardcoded · amarelo = a preencher (Q3-Q4)

Sheet DRE
A1: DRE Consolidado 2026 · com sazonalidade
A3: Linha | B3: Q1 | C3: Q2 | D3: Q3 | E3: Q4 | F3: Total ano
A4: Receita bruta | B4: =Receita!B8 | C4: =Receita!C8 | D4: =Receita!D8 | E4: =Receita!E8 | F4: =SUM(B4:E4)
A5: (-) Custos totais | B5: =-Custos!B8 | C5: =-Custos!C8 | D5: =-Custos!D8 | E5: =-Custos!E8 | F5: =SUM(B5:E5)
A6: Margem bruta | B6: =B4+B5 | C6: =C4+C5 | D6: =D4+D5 | E6: =E4+E5 | F6: =F4+F5
A7: Ajuste sazonalidade | B7: =B6*(Sazonal!B4-1) | C7: =C6*(Sazonal!B5-1) | D7: =D6*(Sazonal!B6-1) | E7: =E6*(Sazonal!B7-1) | F7: =SUM(B7:E7)
A8: Margem líquida | B8: =B6+B7 | C8: =C6+C7 | D8: =D6+D7 | E8: =E6+E7 | F8: =F6+F7
A10: Margem % | B10: =IFERROR(B8/B4, 0) | C10: =IFERROR(C8/C4, 0) | D10: =IFERROR(D8/D4, 0) | E10: =IFERROR(E8/E4, 0) | F10: =IFERROR(F8/F4, 0)
A12: Verde = puxa de outra aba · Amarelo = ajuste sazonal ativo

Sheet KPIs
A1: KPIs derivados
A3: Indicador | B3: Q1 | C3: Q2 | D3: Q3 | E3: Q4 | F3: Ano
A4: Entregas concluídas (nº) | B4: 186 | C4: 214 | F4: =SUM(B4:E4)
A5: Ticket médio (R$/entrega) | B5: =IFERROR(DRE!B4/B4, 0) | C5: =IFERROR(DRE!C4/C4, 0) | D5: =IFERROR(DRE!D4/D4, 0) | E5: =IFERROR(DRE!E4/E4, 0) | F5: =IFERROR(DRE!F4/F4, 0)
A6: Custo por entrega (R$) | B6: =IFERROR(-DRE!B5/B4, 0) | C6: =IFERROR(-DRE!C5/C4, 0) | D6: =IFERROR(-DRE!D5/D4, 0) | E6: =IFERROR(-DRE!E5/E4, 0) | F6: =IFERROR(-DRE!F5/F4, 0)
A7: Margem líquida % | B7: =DRE!B10 | C7: =DRE!C10 | D7: =DRE!D10 | E7: =DRE!E10 | F7: =DRE!F10
A9: Verde = fórmula puxando de outra aba · Azul = hardcoded · Amarelo = premissa-chave
